qubipy/__init__.py
qubipy/config.py
qubipy/endpoints_core.py
qubipy/endpoints_rpc.py
qubipy/exceptions.py
qubipy/utils.py
qubipy/core/__init__.py
qubipy/core/core_client.py
qubipy/crypto/__init__.py
qubipy/crypto/crypto.dll
qubipy/crypto/crypto.so
qubipy/crypto/crypto_intel.dylib
qubipy/crypto/crypto_silicon.dylib
qubipy/crypto/utils.py
qubipy/rpc/__init__.py
qubipy/rpc/rpc_client.py
qubipy/tx/__init__.py
qubipy/tx/builder.py
qubipy/tx/utils.py
qubipy-0.4.1.dist-info/licenses/LICENSE
qubipy-0.4.1.dist-info/METADATA
qubipy-0.4.1.dist-info/WHEEL
qubipy-0.4.1.dist-info/top_level.txt
qubipy-0.4.1.dist-info/RECORD
