Metadata-Version: 2.4
Name: QubiPy
Version: 0.4.1
Summary: QubiPy, a Python Library for the QUBIC RPC API
Home-page: https://github.com/QubiPy-Labs/QubiPy
Author: Kyoto
Author-email: qubipy.labs@gmail.com
Project-URL: Documentation, https://qubipy.readthedocs.io
Project-URL: Source Code, https://github.com/QubiPy-Labs/QubiPy
Project-URL: Bug Tracker, https://github.com/QubiPy-Labs/QubiPy/issues
Keywords: qubic,blockchain,rpc,api,cryptocurrency
Classifier: Development Status :: 4 - Beta
Classifier: Intended Audience :: Developers
Classifier: License :: OSI Approved :: GNU Affero General Public License v3
Classifier: Programming Language :: Python :: 3
Classifier: Programming Language :: Python :: 3.10
Classifier: Programming Language :: Python :: 3.11
Classifier: Operating System :: OS Independent
Classifier: Topic :: Software Development :: Libraries :: Python Modules
Classifier: Topic :: Internet
Requires-Python: >=3.10
License-File: LICENSE
Requires-Dist: requests>=2.32.3
Requires-Dist: urllib3>=2.2.3
Dynamic: author
Dynamic: author-email
Dynamic: classifier
Dynamic: description
Dynamic: description-content-type
Dynamic: home-page
Dynamic: keywords
Dynamic: license-file
Dynamic: project-url
Dynamic: requires-dist
Dynamic: requires-python
Dynamic: summary
